metvae/__init__.py
metvae/cli.py
metvae/compute_corr.py
metvae/impute_missing.py
metvae/model.py
metvae/sim.py
metvae/sparse.py
metvae/utils.py
metvae/vae.py
metvae/tests/__init__.py
metvae/tests/conftest.py
metvae/tests/test_cli.py
metvae/tests/test_model.py
metvae-0.0.2.dist-info/licenses/LICENSE
metvae-0.0.2.dist-info/METADATA
metvae-0.0.2.dist-info/WHEEL
metvae-0.0.2.dist-info/entry_points.txt
metvae-0.0.2.dist-info/top_level.txt
metvae-0.0.2.dist-info/RECORD
