Metadata-Version: 2.4
Name: metvae
Version: 0.0.2
Summary: Metabolomics Variational Autoencoders.
Home-page: https://github.com/FrederickHuangLin/MetVAE-PyPI
Author: Huang Lin
Author-email: huanglinfrederick@gmail.com
Maintainer: Huang Lin
Maintainer-email: huanglinfrederick@gmail.com
License: MIT
Classifier: License :: OSI Approved :: MIT License
Classifier: Topic :: Software Development :: Libraries
Classifier: Topic :: Scientific/Engineering
Classifier: Topic :: Scientific/Engineering :: Bio-Informatics
Classifier: Programming Language :: Python :: 3
Classifier: Operating System :: OS Independent
Requires-Python: >=3.9
License-File: LICENSE
Requires-Dist: joblib>=1.2.0
Requires-Dist: numpy>=1.20.0
Requires-Dist: scipy
Requires-Dist: statsmodels
Requires-Dist: tensorboard
Requires-Dist: tqdm
Requires-Dist: pandas>=1.0.0
Requires-Dist: torch>=1.8.0
Requires-Dist: pytorch-lightning>=1.3.1
Requires-Dist: networkx>=2.6
Dynamic: author
Dynamic: author-email
Dynamic: classifier
Dynamic: description
Dynamic: description-content-type
Dynamic: home-page
Dynamic: license
Dynamic: license-file
Dynamic: maintainer
Dynamic: maintainer-email
Dynamic: requires-dist
Dynamic: requires-python
Dynamic: summary
